{
"meta":{"test_sets":[],"test_metrics":[],"learn_metrics":[{"best_value":"Min","name":"RMSE"}],"launch_mode":"Train","parameters":"","iteration_count":100,"learn_sets":["learn"],"name":"experiment"},
"iterations":[
{"learn":[14.005006],"iteration":0,"passed_time":0.0008369373212,"remaining_time":0.0828567948},
{"learn":[13.14441192],"iteration":1,"passed_time":0.00155472154,"remaining_time":0.07618135547},
{"learn":[12.34258257],"iteration":2,"passed_time":0.002302514466,"remaining_time":0.07444796773},
{"learn":[11.64527793],"iteration":3,"passed_time":0.002951063238,"remaining_time":0.07082551771},
{"learn":[11.02766183],"iteration":4,"passed_time":0.003696391342,"remaining_time":0.07023143549},
{"learn":[10.43485794],"iteration":5,"passed_time":0.004371251587,"remaining_time":0.06848294154},
{"learn":[9.890641275],"iteration":6,"passed_time":0.005089636983,"remaining_time":0.06761946277},
{"learn":[9.492161212],"iteration":7,"passed_time":0.005911274372,"remaining_time":0.06797965528},
{"learn":[9.105082953],"iteration":8,"passed_time":0.006676852091,"remaining_time":0.06751039336},
{"learn":[8.674157135],"iteration":9,"passed_time":0.007388273863,"remaining_time":0.06649446476},
{"learn":[8.341743544],"iteration":10,"passed_time":0.008220752461,"remaining_time":0.06651336082},
{"learn":[8.049372916],"iteration":11,"passed_time":0.00906505419,"remaining_time":0.06647706406},
{"learn":[7.757318612],"iteration":12,"passed_time":0.00977350014,"remaining_time":0.06540727017},
{"learn":[7.522206899],"iteration":13,"passed_time":0.01054365682,"remaining_time":0.06476817759},
{"learn":[7.297756655],"iteration":14,"passed_time":0.01130659938,"remaining_time":0.06407072982},
{"learn":[7.088359431],"iteration":15,"passed_time":0.0120570475,"remaining_time":0.06329949937},
{"learn":[6.882113791],"iteration":16,"passed_time":0.01281322683,"remaining_time":0.06255869571},
{"learn":[6.704728832],"iteration":17,"passed_time":0.01354528898,"remaining_time":0.06170631648},
{"learn":[6.563881962],"iteration":18,"passed_time":0.01432206862,"remaining_time":0.06105723989},
{"learn":[6.418790279],"iteration":19,"passed_time":0.01503294933,"remaining_time":0.06013179732},
{"learn":[6.315756953],"iteration":20,"passed_time":0.01579196421,"remaining_time":0.05940786536},
{"learn":[6.210157751],"iteration":21,"passed_time":0.01653004814,"remaining_time":0.05860653432},
{"learn":[6.115058449],"iteration":22,"passed_time":0.01720841525,"remaining_time":0.05761078148},
{"learn":[6.014819884],"iteration":23,"passed_time":0.01793564795,"remaining_time":0.05679621851},
{"learn":[5.93117229],"iteration":24,"passed_time":0.01871740733,"remaining_time":0.05615222198},
{"learn":[5.844857622],"iteration":25,"passed_time":0.01939997265,"remaining_time":0.05521530676},
{"learn":[5.771145213],"iteration":26,"passed_time":0.02010324848,"remaining_time":0.05435322738},
{"learn":[5.704018229],"iteration":27,"passed_time":0.02079208607,"remaining_time":0.05346536418},
{"learn":[5.665806474],"iteration":28,"passed_time":0.02147849892,"remaining_time":0.05258529045},
{"learn":[5.616500369],"iteration":29,"passed_time":0.02228437547,"remaining_time":0.05199687611},
{"learn":[5.558023666],"iteration":30,"passed_time":0.02305215751,"remaining_time":0.0513096409},
{"learn":[5.510080976],"iteration":31,"passed_time":0.0237852617,"remaining_time":0.0505436811},
{"learn":[5.468747792],"iteration":32,"passed_time":0.0245929017,"remaining_time":0.04993104285},
{"learn":[5.429275534],"iteration":33,"passed_time":0.02532748879,"remaining_time":0.0491651253},
{"learn":[5.402117324],"iteration":34,"passed_time":0.02621449406,"remaining_time":0.0486840604},
{"learn":[5.367635151],"iteration":35,"passed_time":0.02708176072,"remaining_time":0.04814535239},
{"learn":[5.345181232],"iteration":36,"passed_time":0.02801694023,"remaining_time":0.04770451986},
{"learn":[5.319151269],"iteration":37,"passed_time":0.0288090699,"remaining_time":0.04700427193},
{"learn":[5.296134146],"iteration":38,"passed_time":0.02949257706,"remaining_time":0.0461294154},
{"learn":[5.269629003],"iteration":39,"passed_time":0.03029145993,"remaining_time":0.0454371899},
{"learn":[5.251147059],"iteration":40,"passed_time":0.03099208057,"remaining_time":0.04459835985},
{"learn":[5.248003302],"iteration":41,"passed_time":0.03138867644,"remaining_time":0.04334626747},
{"learn":[5.232376509],"iteration":42,"passed_time":0.03215173924,"remaining_time":0.04261974737},
{"learn":[5.213524255],"iteration":43,"passed_time":0.03286593644,"remaining_time":0.04182937366},
{"learn":[5.189691584],"iteration":44,"passed_time":0.03364095263,"remaining_time":0.04111671988},
{"learn":[5.166052198],"iteration":45,"passed_time":0.03438055954,"remaining_time":0.04035978728},
{"learn":[5.140406659],"iteration":46,"passed_time":0.03517999349,"remaining_time":0.03967105649},
{"learn":[5.118929684],"iteration":47,"passed_time":0.03598627083,"remaining_time":0.03898512673},
{"learn":[5.108792602],"iteration":48,"passed_time":0.03672828245,"remaining_time":0.03822739602},
{"learn":[5.098141225],"iteration":49,"passed_time":0.03747852016,"remaining_time":0.03747852016},
{"learn":[5.085926393],"iteration":50,"passed_time":0.03819771714,"remaining_time":0.03669976745},
{"learn":[5.067816804],"iteration":51,"passed_time":0.03900129921,"remaining_time":0.03600119927},
{"learn":[5.049834901],"iteration":52,"passed_time":0.039796054,"remaining_time":0.03529084034},
{"learn":[5.03838627],"iteration":53,"passed_time":0.04048927016,"remaining_time":0.03449085977},
{"learn":[5.033534248],"iteration":54,"passed_time":0.0409951899,"remaining_time":0.03354151901},
{"learn":[5.023726885],"iteration":55,"passed_time":0.04172172123,"remaining_time":0.0327813524},
{"learn":[5.01290392],"iteration":56,"passed_time":0.04242313342,"remaining_time":0.03200341644},
{"learn":[5.005569127],"iteration":57,"passed_time":0.04317104659,"remaining_time":0.03126179235},
{"learn":[4.989969032],"iteration":58,"passed_time":0.04395808629,"remaining_time":0.03054714471},
{"learn":[4.976762446],"iteration":59,"passed_time":0.04468463766,"remaining_time":0.02978975844},
{"learn":[4.967222715],"iteration":60,"passed_time":0.04543581721,"remaining_time":0.02904912904},
{"learn":[4.954407599],"iteration":61,"passed_time":0.04618838949,"remaining_time":0.02830901291},
{"learn":[4.942125056],"iteration":62,"passed_time":0.04691640372,"remaining_time":0.02755407838},
{"learn":[4.930230716],"iteration":63,"passed_time":0.04760832735,"remaining_time":0.02677968413},
{"learn":[4.921695642],"iteration":64,"passed_time":0.04831980924,"remaining_time":0.02601835882},
{"learn":[4.906405625],"iteration":65,"passed_time":0.04909474526,"remaining_time":0.02529123241},
{"learn":[4.894330248],"iteration":66,"passed_time":0.04983019404,"remaining_time":0.0245432299},
{"learn":[4.88211557],"iteration":67,"passed_time":0.05056826795,"remaining_time":0.02379683198},
{"learn":[4.877946398],"iteration":68,"passed_time":0.05127851743,"remaining_time":0.0230381745},
{"learn":[4.863182126],"iteration":69,"passed_time":0.05203733192,"remaining_time":0.02230171368},
{"learn":[4.84646533],"iteration":70,"passed_time":0.05277186891,"remaining_time":0.02155470702},
{"learn":[4.838014752],"iteration":71,"passed_time":0.05356639326,"remaining_time":0.02083137516},
{"learn":[4.82981137],"iteration":72,"passed_time":0.05428190303,"remaining_time":0.02007686824},
{"learn":[4.817094767],"iteration":73,"passed_time":0.05502833329,"remaining_time":0.01933427926},
{"learn":[4.808314151],"iteration":74,"passed_time":0.05578949236,"remaining_time":0.01859649745},
{"learn":[4.796235023],"iteration":75,"passed_time":0.05650577364,"remaining_time":0.01784392852},
{"learn":[4.784434534],"iteration":76,"passed_time":0.05720997128,"remaining_time":0.01708869272},
{"learn":[4.774402487],"iteration":77,"passed_time":0.0580298352,"remaining_time":0.01636738942},
{"learn":[4.76731896],"iteration":78,"passed_time":0.05890060496,"remaining_time":0.01565712284},
{"learn":[4.75934113],"iteration":79,"passed_time":0.05961366995,"remaining_time":0.01490341749},
{"learn":[4.754106378],"iteration":80,"passed_time":0.06037529368,"remaining_time":0.01416210592},
{"learn":[4.744002932],"iteration":81,"passed_time":0.06114116823,"remaining_time":0.01342123205},
{"learn":[4.731700554],"iteration":82,"passed_time":0.06184729339,"remaining_time":0.01266751792},
{"learn":[4.723284153],"iteration":83,"passed_time":0.06257062847,"remaining_time":0.01191821495},
{"learn":[4.712232782],"iteration":84,"passed_time":0.06335761432,"remaining_time":0.01118075547},
{"learn":[4.703046867],"iteration":85,"passed_time":0.06419715047,"remaining_time":0.01045069891},
{"learn":[4.698601855],"iteration":86,"passed_time":0.06488321263,"remaining_time":0.009695192692},
{"learn":[4.692429407],"iteration":87,"passed_time":0.06558658866,"remaining_time":0.008943625727},
{"learn":[4.675027364],"iteration":88,"passed_time":0.06627397341,"remaining_time":0.008191165253},
{"learn":[4.662368584],"iteration":89,"passed_time":0.06692516736,"remaining_time":0.007436129707},
{"learn":[4.646206172],"iteration":90,"passed_time":0.06759192175,"remaining_time":0.006684915338},
{"learn":[4.641245848],"iteration":91,"passed_time":0.06826042957,"remaining_time":0.005935689527},
{"learn":[4.633900435],"iteration":92,"passed_time":0.06897068906,"remaining_time":0.005191342188},
{"learn":[4.624738236],"iteration":93,"passed_time":0.06960385775,"remaining_time":0.004442799431},
{"learn":[4.612798287],"iteration":94,"passed_time":0.07028738495,"remaining_time":0.00369933605},
{"learn":[4.605222001],"iteration":95,"passed_time":0.07090962225,"remaining_time":0.002954567594},
{"learn":[4.601725912],"iteration":96,"passed_time":0.07151436532,"remaining_time":0.002211784494},
{"learn":[4.59722371],"iteration":97,"passed_time":0.0721984436,"remaining_time":0.001473437624},
{"learn":[4.580235665],"iteration":98,"passed_time":0.07285587976,"remaining_time":0.0007359179774},
{"learn":[4.57591791],"iteration":99,"passed_time":0.07349632267,"remaining_time":0}
]}